pyregeon/__init__.py
pyregeon/settings.py
pyregeon-0.2.1.dist-info/licenses/LICENSE
pyregeon-0.2.1.dist-info/WHEEL
pyregeon-0.2.1.dist-info/METADATA
pyregeon-0.2.1.dist-info/RECORD
