Metadata-Version: 2.4
Name: pyregeon
Version: 0.2.1
Summary: Reusable Python utilities to work with geospatial regions.
Author: Martí Bosch
Author-email: Martí Bosch <marti.bosch@epfl.ch>
License-Expression: GPL-3.0-or-later
License-File: LICENSE
Classifier: License :: OSI Approved :: GNU General Public License v3 (GPLv3)
Classifier: Natural Language :: English
Classifier: Programming Language :: Python :: 3
Classifier: Programming Language :: Python :: 3.10
Classifier: Programming Language :: Python :: 3.11
Classifier: Programming Language :: Python :: 3.12
Classifier: Programming Language :: Python :: 3.13
Requires-Dist: geopandas>=1.0.0
Requires-Dist: build ; extra == 'dev'
Requires-Dist: commitizen ; extra == 'dev'
Requires-Dist: pip ; extra == 'dev'
Requires-Dist: pre-commit ; extra == 'dev'
Requires-Dist: toml ; extra == 'dev'
Requires-Dist: twine ; extra == 'dev'
Requires-Dist: myst-parser ; extra == 'doc'
Requires-Dist: nbsphinx ; extra == 'doc'
Requires-Dist: pydata-sphinx-theme ; extra == 'doc'
Requires-Dist: sphinx ; extra == 'doc'
Requires-Dist: sphinxemoji ; extra == 'doc'
Requires-Dist: osmnx ; extra == 'ox'
Requires-Dist: coverage[toml] ; extra == 'test'
Requires-Dist: pytest ; extra == 'test'
Requires-Dist: pytest-cov ; extra == 'test'
Requires-Dist: ruff ; extra == 'test'
Project-URL: Repository, https://github.com/martibosch/pyregeon
Provides-Extra: dev
Provides-Extra: doc
Provides-Extra: ox
Provides-Extra: test
